representational_toolkit/__init__.py
representational_toolkit/analysis.py
representational_toolkit/cka_analysis.py
representational_toolkit/fisher_analysis.py
representational_toolkit/pca_shift_analysis.py
representational_toolkit/pca_sim_analysis.py
representational_toolkit/test.py
representational_analysis-0.1.3.dist-info/METADATA
representational_analysis-0.1.3.dist-info/WHEEL
representational_analysis-0.1.3.dist-info/entry_points.txt
representational_analysis-0.1.3.dist-info/top_level.txt
representational_analysis-0.1.3.dist-info/RECORD
